anisocado/__init__.py
anisocado/_anisocado.py
anisocado/misc.py
anisocado/psf.py
anisocado/psf_utils.py
anisocado/pupil_utils.py
anisocado/tests/__init__.py
anisocado/tests/test_playing_around.py
anisocado/tests/test_psf_functions.py
anisocado/tests/test_scao_psf.py
anisocado-0.5.0.dist-info/LICENSE
anisocado-0.5.0.dist-info/METADATA
anisocado-0.5.0.dist-info/WHEEL
anisocado-0.5.0.dist-info/RECORD
