Metadata-Version: 2.3
Name: AnisoCADO
Version: 0.5.0
Summary: Generate off-axis SCAO PSFs for the ELT
License: GPL-3.0-or-later
Keywords: astronomy
Author: Kieran Leschinski
Author-email: kieran.leschinski@unive.ac.at
Maintainer: Kieran Leschinski
Maintainer-email: kieran.leschinski@unive.ac.at
Requires-Python: >=3.10,<3.15
Classifier: Intended Audience :: Science/Research
Classifier: License :: OSI Approved :: GNU General Public License v3 or later (GPLv3+)
Classifier: Operating System :: OS Independent
Classifier: Programming Language :: Python :: 3
Classifier: Programming Language :: Python :: 3.10
Classifier: Programming Language :: Python :: 3.11
Classifier: Programming Language :: Python :: 3.12
Classifier: Programming Language :: Python :: 3.13
Classifier: Topic :: Scientific/Engineering :: Astronomy
Requires-Dist: astropy (>=6.1.7,<8.0.0)
Requires-Dist: matplotlib (>=3.10.1,<4.0.0)
Requires-Dist: numpy (>=1.26.4,<2.3.0) ; python_version >= "3.10" and python_version < "3.13"
Requires-Dist: numpy (>=2.2.6,<3.0.0) ; python_version >= "3.13"
Project-URL: Bug Tracker, https://github.com/AstarVienna/AnisoCADO/issues
Project-URL: Changelog, https://github.com/AstarVienna/AnisoCADO/releases
Project-URL: Documentation, https://anisocado.readthedocs.io/en/latest/
Project-URL: Repository, https://github.com/AstarVienna/AnisoCADO/
